cpp_easygraph.cp313-win32.pyd
easygraph/__init__.py
easygraph/_global.py
easygraph/convert.py
easygraph/exception.py
easygraph/classes/__init__.py
easygraph/classes/base.py
easygraph/classes/directed_graph.py
easygraph/classes/directed_multigraph.py
easygraph/classes/graph.py
easygraph/classes/graphviews.py
easygraph/classes/hypergraph.py
easygraph/classes/multigraph.py
easygraph/classes/operation.py
easygraph/classes/test_base_graph_class.py
easygraph/classes/tests/__init__.py
easygraph/classes/tests/test_base.py
easygraph/classes/tests/test_directed_graph.py
easygraph/classes/tests/test_graph.py
easygraph/classes/tests/test_graphV2.py
easygraph/classes/tests/test_hypergraph.py
easygraph/classes/tests/test_multidigraph.py
easygraph/classes/tests/test_multigraph.py
easygraph/classes/tests/test_operation.py
easygraph/datapipe/__init__.py
easygraph/datapipe/common.py
easygraph/datapipe/loader.py
easygraph/datapipe/normalize.py
easygraph/datasets/__init__.py
easygraph/datasets/amazon_photo.py
easygraph/datasets/arxiv.py
easygraph/datasets/citation_graph.py
easygraph/datasets/coauthor.py
easygraph/datasets/facebook_ego.py
easygraph/datasets/flickr.py
easygraph/datasets/get_sample_graph.py
easygraph/datasets/github.py
easygraph/datasets/gnn_benchmark.py
easygraph/datasets/graph_dataset_base.py
easygraph/datasets/karate.py
easygraph/datasets/ppi.py
easygraph/datasets/reddit.py
easygraph/datasets/roadnet.py
easygraph/datasets/twitter_ego.py
easygraph/datasets/utils.py
easygraph/datasets/web_google.py
easygraph/datasets/wiki_topcats.py
easygraph/datasets/dynamic/__init__.py
easygraph/datasets/dynamic/email_enron.py
easygraph/datasets/dynamic/email_eu.py
easygraph/datasets/dynamic/hospital_lyon.py
easygraph/datasets/dynamic/load_dataset.py
easygraph/datasets/hypergraph/House_Committees.py
easygraph/datasets/hypergraph/Yelp.py
easygraph/datasets/hypergraph/__init__.py
easygraph/datasets/hypergraph/_global.py
easygraph/datasets/hypergraph/cat_edge_Cooking.py
python_easygraph-1.6.dist-info/licenses/LICENSE
python_easygraph-1.6.dist-info/METADATA
python_easygraph-1.6.dist-info/WHEEL
python_easygraph-1.6.dist-info/top_level.txt
python_easygraph-1.6.dist-info/RECORD
