Metadata-Version: 2.1
Name: Python-EasyGraph
Version: 1.6
Summary: Easy Graph
Home-page: https://github.com/easy-graph/Easy-Graph
Author: Fudan DataNET Group
Author-email: mgao21@m.fudan.edu.cn
Classifier: Programming Language :: Python :: 3.8
Classifier: Programming Language :: Python :: 3.9
Classifier: Programming Language :: Python :: 3.10
Classifier: Programming Language :: Python :: 3.11
Classifier: Programming Language :: Python :: 3.12
Classifier: Programming Language :: Python :: 3.13
Classifier: Programming Language :: Python :: 3.14
Classifier: License :: OSI Approved :: BSD License
Classifier: Operating System :: OS Independent
Requires-Python: >=3.8, <3.15
License-File: LICENSE
Requires-Dist: tqdm>=4.49.0
Requires-Dist: joblib>=1.2.0
Requires-Dist: six>=1.16.0
Requires-Dist: progressbar33>=2.4
Requires-Dist: progressbar>=2.5
Requires-Dist: nose>=0.10.1
Requires-Dist: matplotlib
Requires-Dist: requests
Requires-Dist: optuna
Requires-Dist: numpy>=1.23; python_version < "3.14"
Requires-Dist: gensim>=4.3.3; python_version < "3.14"
Requires-Dist: pandas<=1.1.5,>=1.0.1; python_version <= "3.7"
Requires-Dist: scikit-learn<=1.0.2,>=0.24.0; python_version == "3.7"
Requires-Dist: scipy<=1.7.3,>=1.5.0; python_version == "3.7"
Requires-Dist: numpy>=2.0; python_version >= "3.14"
Requires-Dist: statsmodels>=0.12.0; python_version >= "3.7" and python_version < "3.14"
Requires-Dist: scikit-learn>=0.24.0; python_version >= "3.8" and python_version < "3.14"
Requires-Dist: scipy>=1.8.0; python_version >= "3.8" and python_version < "3.14"
Requires-Dist: pandas>=1.1.0; python_version >= "3.8" and python_version < "3.14"
Provides-Extra: torch
Requires-Dist: torch>=2.0; extra == "torch"
Requires-Dist: fastjsonschema; extra == "torch"
Requires-Dist: torch-geometric>=2.3; extra == "torch"
